localDNS/__init__.py
localDNS/main.py
localDNS-1.0.2.dist-info/LICENSE
localDNS-1.0.2.dist-info/METADATA
localDNS-1.0.2.dist-info/WHEEL
localDNS-1.0.2.dist-info/top_level.txt
localDNS-1.0.2.dist-info/RECORD
